README.md
setup.py
mutcm.egg-info/PKG-INFO
mutcm.egg-info/SOURCES.txt
mutcm.egg-info/dependency_links.txt
mutcm.egg-info/top_level.txt
src/__init__.py
src/mutcm.py