Metadata-Version: 2.1
Name: mutcm
Version: 0.0.5
Summary: Support for devops
Home-page: https://github.com/muthugit/tcm
Author: Muthupandian
Author-email: contact@muthupandian.in
License: UNKNOWN
Project-URL: Documentation, https://mutcm.readthedocs.io/en/latest/
Project-URL: Author, https://muthupandian.in
Platform: UNKNOWN
Classifier: Programming Language :: Python :: 3
Classifier: License :: OSI Approved :: MIT License
Classifier: Operating System :: OS Independent
Requires-Python: >=3.6
